dataclassish/__init__.py
dataclassish/_version.py
dataclassish/_version.pyi
dataclassish/converters.py
dataclassish/flags.py
dataclassish/py.typed
dataclassish/_src/__init__.py
dataclassish/_src/api.py
dataclassish/_src/converters.py
dataclassish/_src/flag_compat.py
dataclassish/_src/flags.py
dataclassish/_src/register_base.py
dataclassish/_src/register_copyreplace.py
dataclassish/_src/register_dataclass.py
dataclassish/_src/register_mapping.py
dataclassish/_src/types.py
dataclassish-0.7.2.dist-info/METADATA
dataclassish-0.7.2.dist-info/WHEEL
dataclassish-0.7.2.dist-info/licenses/LICENSE
dataclassish-0.7.2.dist-info/RECORD
