Metadata-Version: 2.4
Name: dataclassish
Version: 0.7.2
Summary: dataclass tools, extended by multiple dispatch
Project-URL: Homepage, https://github.com/GalacticDynamics/dataclassish
Project-URL: Bug Tracker, https://github.com/GalacticDynamics/dataclassish/issues
Project-URL: Discussions, https://github.com/GalacticDynamics/dataclassish/discussions
Project-URL: Changelog, https://github.com/GalacticDynamics/dataclassish/releases
Author-email: Nathaniel Starkman <nstarman@users.noreply.github.com>
License: Copyright 2024 Nathaniel Starkman
License-File: LICENSE
Classifier: Development Status :: 1 - Planning
Classifier: Intended Audience :: Developers
Classifier: Intended Audience :: Science/Research
Classifier: License :: OSI Approved :: MIT License
Classifier: Operating System :: OS Independent
Classifier: Programming Language :: Python
Classifier: Programming Language :: Python :: 3
Classifier: Programming Language :: Python :: 3 :: Only
Classifier: Programming Language :: Python :: 3.10
Classifier: Programming Language :: Python :: 3.11
Classifier: Programming Language :: Python :: 3.12
Classifier: Programming Language :: Python :: 3.13
Classifier: Topic :: Scientific/Engineering
Classifier: Typing :: Typed
Requires-Python: >=3.10
Requires-Dist: plum-dispatch>=2.5.1
Requires-Dist: typing-extensions>=4.12.2
